{
  "_template": {
    "_comment": "Template for adding new tokens. Copy an entry below and fill in the fields.",
    "symbol": "TOKEN",
    "name": "Token Name",
    "category": "E or F",
    "decimals": 18,
    "pricing": {
      "method": "par | chainlink | kraken | coingecko",
      "depeg_check_feed": "0x... (Ethereum Chainlink feed, for par-priced E tokens only)",
      "chainlink_feed": "0x... (Ethereum Chainlink feed, for chainlink-priced E tokens)",
      "pyth_feed_id": "0x... (Pyth price feed ID, fallback for chainlink-priced tokens)",
      "kraken_pair": "TOKENUSD (for F tokens with Kraken listing)",
      "coingecko_id": "token-id (CoinGecko coin ID, fallback or primary for F tokens)"
    }
  },

  "ethereum": {
    "native": {
      "symbol": "ETH",
      "name": "Ether",
      "category": "F",
      "decimals": 18,
      "pricing": {
        "method": "kraken",
        "kraken_pair": "ETHUSD",
        "coingecko_id": "ethereum"
      }
    },
    "0xa0b86991c6218b36c1d19d4a2e9eb0ce3606eb48": {
      "symbol": "USDC",
      "name": "USD Coin",
      "category": "E",
      "decimals": 6,
      "pricing": {
        "method": "par",
        "depeg_check_feed": "0x8fFfFfd4AfB6115b954Bd326cbe7B4BA576818f6"
      }
    },
    "0xdac17f958d2ee523a2206206994597c13d831ec7": {
      "symbol": "USDT",
      "name": "Tether USD",
      "category": "E",
      "decimals": 6,
      "pricing": {
        "method": "chainlink",
        "chainlink_feed": "0x3E7d1eAB13ad0104d2750B8863b489D65364e32D",
        "pyth_feed_id": "0x2b89b9dc8fdf9f34592c9f48b082e8e61d65f4d69e2c87a74d6c5c4c4b207a3e",
        "coingecko_id": "tether",
        "_note": "Hierarchy: Chainlink (primary) → Pyth (fallback) → CoinGecko (last-resort) per Section 6.2"
      }
    },
    "0x6b175474e89094c44da98b954eedeac495271d0f": {
      "symbol": "DAI",
      "name": "Dai Stablecoin",
      "category": "E",
      "decimals": 18,
      "pricing": {
        "method": "par",
        "depeg_check_feed": "0xAed0c38402a5d19df6E4c03F4E2DceD6e29c1ee9"
      }
    },
    "0x6c3ea9036406852006290770bedfcaba0e23a0e8": {
      "symbol": "PYUSD",
      "name": "PayPal USD",
      "category": "E",
      "decimals": 6,
      "pricing": {
        "method": "par",
        "depeg_check_feed": null,
        "pyth_feed_id": "0x150ac9b959aee0051e4091f0ef5216d941f590e1c5e7f91cf7635b5c11628c0e",
        "_note": "No free Chainlink PYUSD/USD feed on mainnet. Pyth feed added for depeg monitoring fallback."
      }
    },
    "0x4f8e5de400de08b164e7421b3ee387f461becd1a": {
      "symbol": "USDD",
      "name": "USDD",
      "category": "E",
      "decimals": 18,
      "pricing": {
        "method": "pyth",
        "pyth_feed_id": "0x6d20210495d6518787b72e4ad06bc4df21e68d89a802cf6bced2fca6c29652a6",
        "coingecko_id": "usdd"
      }
    },
    "0x0fedba9178b70e8b54e2af08ebffcf28a1e5a43b": {
      "symbol": "DAM",
      "name": "Reservoir",
      "category": "F",
      "decimals": 18,
      "pricing": {
        "method": "coingecko",
        "coingecko_id": "reservoir"
      }
    },
    "0x58d97b57bb95320f9a05dc918aef65434969c2b2": {
      "symbol": "MORPHO",
      "name": "Morpho",
      "category": "F",
      "decimals": 18,
      "pricing": {
        "method": "kraken",
        "kraken_pair": "MORPHOUSD",
        "coingecko_id": "morpho"
      }
    },
    "0x808507121b80c02388fad14726482e061b8da827": {
      "symbol": "PENDLE",
      "name": "Pendle",
      "category": "F",
      "decimals": 18,
      "pricing": {
        "method": "kraken",
        "kraken_pair": "PENDLEUSD",
        "coingecko_id": "pendle"
      }
    },
    "0x4956b52ae2ff65d74ca2d61207523288e4528f96": {
      "symbol": "RLP",
      "name": "Resolv Liquidity Provider Token",
      "category": "A2",
      "decimals": 18,
      "pricing": {
        "method": "pyth",
        "pyth_feed_id": "0x7265d5cf8ee0e7b5266f75ff19c42c5b7697a9756c9304aa78b6be4fbb8d823d",
        "coingecko_id": "resolv-rlp",
        "expected_update_freq_hours": 24,
        "_note": "A2 NAV-based. No on-chain convertToAssets. Hierarchy: Pyth (primary) → CoinGecko (fallback) → DEX TWAP (last-resort per Section 6.2). RLP trades on Curve/Uniswap."
      }
    },
    "0x238a700ed6165261cf8b2e544ba797bc11e466ba": {
      "symbol": "mF-ONE",
      "name": "Midas Fasanara ONE",
      "category": "A2",
      "decimals": 18,
      "pricing": {
        "method": "chainlink",
        "chainlink_feed": "0x8D51DBC85cEef637c97D02bdaAbb5E274850e68C",
        "expected_update_freq_hours": 24,
        "_note": "Midas Chainlink-style oracle for mF-ONE/USD. Token held in wallet 0xa33e after Morpho market closure.",
        "_fallback_note": "Primary is Midas Chainlink-style oracle. No Pyth/Redstone/CoinGecko feeds available for this token."
      }
    },
    "0x2fe058ccf29f123f9dd2aec0418aa66a877d8e50": {
      "symbol": "msyrupUSDp",
      "name": "Plasma syrupUSD Pre-deposit Midas Vault",
      "category": "A2",
      "decimals": 18,
      "pricing": {
        "method": "chainlink",
        "chainlink_feed": "0x337d914ff6622510FC2C63ac59c1D07983895241",
        "expected_update_freq_hours": 168,
        "_note": "Midas Chainlink-style oracle, NAV updated 1-2x/week, expected update frequency ~168h",
        "_fallback_note": "No Pyth or CoinGecko feed exists for msyrupUSDp. Midas oracle is the only available source."
      }
    },
    "0x32e616f4f17d43f9a5cd9be0e294727187064cb3": {
      "symbol": "DUSDUSDC",
      "name": "Curve DUSD/USDC LP",
      "category": "C",
      "decimals": 18,
      "pricing": {
        "method": "curve_lp",
        "pool_address": "0x32e616f4f17d43f9a5cd9be0e294727187064cb3",
        "constituents": ["USDC", "DUSD"],
        "constituent_addresses": [
          "0xA0b86991c6218b36c1d19D4a2e9Eb0cE3606eB48",
          "0x1e33E98aF620F1D563fcD3cfd3C75acE841204ef"
        ],
        "_note": "Category C LP. Decompose into constituents and price each. Virtual price available via get_virtual_price(). DUSD has depegged significantly."
      }
    },
    "0x14d60e7fdc0d71d8611742720e4c50e7a974020c": {
      "symbol": "USCC",
      "name": "Superstate Crypto Carry Fund",
      "category": "A2",
      "decimals": 6,
      "pricing": {
        "method": "pyth",
        "pyth_feed_id": "0x5d73a5953dc86c4773adc778c30e8a6dfc94c5c3a74d7ebb56dd5e70350f044a",
        "coingecko_id": "superstate-uscc",
        "expected_update_freq_hours": 24,
        "issuer_nav_url": "https://superstate.com/assets/uscc",
        "cross_ref_url": "https://superstate.com/assets/uscc",
        "_note": "A2 NAV-based. Hierarchy: Pyth (primary) → Superstate daily NAV (tier 2 issuer) → CoinGecko (fallback). Chainlink NAVLink (uscc-nav.data.eth) is SmartData (paid), not a free Data Feed — cross-reference only."
      }
    },
    "0x00000000efe302beaa2b3e6e1b18d08d69a9012a": {
      "symbol": "AUSD",
      "name": "Agora Dollar",
      "category": "E",
      "decimals": 6,
      "pricing": {
        "method": "par",
        "pyth_feed_id": "0xd9912df360b5b7f21a122f15bdd5e27f62ce5e72bd316c291f7c86620e07fb2a",
        "coingecko_id": "agora-dollar",
        "_note": "Fiat-backed stablecoin, 1:1 USD peg. Same contract address on multiple EVM chains. Pyth feed used for depeg monitoring."
      }
    },
    "0x8292bb45bf1ee4d140127049757c2e0ff06317ed": {
      "symbol": "RLUSD",
      "name": "Ripple USD",
      "category": "E",
      "decimals": 18,
      "pricing": {
        "method": "par",
        "pyth_feed_id": "0x65652029e7acde632e80192dcaa6ea88e61d84a4c78a982a63e98f4bbcb288d5",
        "coingecko_id": "ripple-usd",
        "_note": "Issued by Standard Custody & Trust Company (Ripple Labs subsidiary). Par-priced. Pyth feed used for depeg monitoring."
      }
    },
    "0x80ac24aa929eaf5013f6436cda2a7ba190f5cc0b": {
      "symbol": "syrupUSDC",
      "name": "Syrup USDC",
      "category": "A2",
      "decimals": 6,
      "pricing": {
        "method": "pyth",
        "pyth_feed_id": "0xe616297dab48626eaacf6d030717b25823b13ae6520b83f4735bf8deec8e2c9a",
        "coingecko_id": "syrupusdc",
        "expected_update_freq_hours": 24,
        "cross_ref_url": "https://app.maple.finance/earn",
        "_note": "Maple yield-bearing USDC vault token. Pyth as primary, issuer price as cross-reference."
      }
    },
    "0xbeeff047c03714965a54b671a37c18bef6b96210": {
      "symbol": "bbqSUDCreservoir",
      "name": "Steakhouse Reservoir USDC",
      "category": "A1",
      "decimals": 18,
      "pricing": {
        "method": "a1_exchange_rate",
        "underlying": "USDC",
        "exchange_rate_contract": "0xBEeFF047C03714965a54b671A37C18beF6b96210",
        "exchange_rate_function": "convertToAssets",
        "_note": "Steakhouse/Morpho MetaMorpho vault (ERC-4626). Underlying USDC priced at par."
      }
    },
    "0xbeef047a543e45807105e51a8bbefcc5950fcfba": {
      "symbol": "steakUSDT",
      "name": "Steakhouse USDT",
      "category": "A1",
      "decimals": 18,
      "pricing": {
        "method": "a1_exchange_rate",
        "underlying": "USDT",
        "exchange_rate_contract": "0xbEef047a543E45807105E51A8BBEFCc5950fcfBa",
        "exchange_rate_function": "convertToAssets",
        "_note": "Steakhouse/Morpho MetaMorpho vault (ERC-4626). Underlying USDT priced via Chainlink."
      }
    },
    "0xc26a6fa2c37b38e549a4a1807543801db684f99c": {
      "symbol": "AA_FalconXUSDC",
      "name": "Pareto AA Tranche - FalconXUSDC",
      "category": "A3",
      "decimals": 18,
      "pricing": {
        "method": "pareto_tranche_price",
        "price_contract": "0x433d5b175148da32ffe1e1a37a939e1b7e79be4d",
        "price_function": "tranchePrice",
        "price_decimals": 6,
        "_note": "Private credit tranche token. On-chain tranche price is cross-reference only. Primary valuation is manual accrual."
      }
    },
    "0x00000000d8f3d6c5dfeb2d2b5ed2276095f3af44": {
      "symbol": "gpAAFalconX",
      "name": "Gauntlet AAFalconX Vault",
      "category": "A3",
      "decimals": 18,
      "pricing": {
        "method": "gauntlet_pro_rata",
        "_note": "Custom vault (NOT ERC-4626). Veris share = balanceOf/totalSupply of vault net exposure. Primary valuation is manual accrual."
      }
    },
    "0x08b798c40b9ab931356d9ab4235f548325c4cb80": {
      "symbol": "aHorRwaUSCC",
      "name": "Aave Horizon RWA USCC",
      "category": "D",
      "decimals": 6,
      "pricing": {
        "method": "pyth",
        "pyth_feed_id": "0x5d73a5953dc86c4773adc778c30e8a6dfc94c5c3a74d7ebb56dd5e70350f044a",
        "coingecko_id": "superstate-uscc",
        "_note": "Aave Horizon aToken for USCC. Balance = supplied USCC + accrued interest. Collateral side of D position. Priced same as USCC (A2)."
      }
    },
    "0xace8a1c0ec12ae81814377491265b47f4ee5d3dd": {
      "symbol": "variableDebtHorRwaRLUSD",
      "name": "Aave Horizon RWA Variable Debt RLUSD",
      "category": "D",
      "decimals": 18,
      "pricing": {
        "method": "par",
        "pyth_feed_id": "0x65652029e7acde632e80192dcaa6ea88e61d84a4c78a982a63e98f4bbcb288d5",
        "coingecko_id": "ripple-usd",
        "_note": "Aave Horizon variable debt token for RLUSD. Balance = borrowed RLUSD + accrued interest. Debt side of D position. Pyth feed for depeg monitoring."
      }
    },
    "0x4c9edd5852cd905f086c759e8383e09bff1e68b3": {
      "symbol": "USDe",
      "name": "USDe",
      "category": "E",
      "decimals": 18,
      "pricing": {
        "method": "chainlink",
        "chainlink_feed": "0xa569d910839Ae8C109eDAA97c4eBB6a00b60C10c",
        "coingecko_id": "ethena-usde",
        "_note": "Ethena USDe on Ethereum. Also 9.99 USDe in sUSDe cooldown (claimable since 22/01/2026)."
      }
    },
    "0x9d39a5de30e57443bff2a8307a4256c8797a3497": {
      "symbol": "sUSDe",
      "name": "Staked USDe",
      "category": "A1",
      "decimals": 18,
      "pricing": {
        "method": "a1_exchange_rate",
        "underlying": "USDe",
        "exchange_rate_contract": "0x9d39a5de30e57443bff2a8307a4256c8797a3497",
        "exchange_rate_function": "convertToAssets",
        "coingecko_id": "ethena-staked-usde",
        "_note": "ERC-4626 vault. On-chain exchange rate is authoritative (A1). Check cooldowns(address) for pending unstakes."
      }
    }
  },

  "arbitrum": {
    "native": {
      "symbol": "ETH",
      "name": "Ether",
      "category": "F",
      "decimals": 18,
      "pricing": {
        "method": "kraken",
        "kraken_pair": "ETHUSD",
        "coingecko_id": "ethereum"
      }
    },
    "0xaf88d065e77c8cc2239327c5edb3a432268e5831": {
      "symbol": "USDC",
      "name": "USD Coin",
      "category": "E",
      "decimals": 6,
      "pricing": {
        "method": "par",
        "depeg_check_feed": "0x8fFfFfd4AfB6115b954Bd326cbe7B4BA576818f6"
      }
    },
    "0xfd086bc7cd5c481dcc9c85ebe478a1c0b69fcbb9": {
      "symbol": "USDT",
      "name": "Tether USD",
      "category": "E",
      "decimals": 6,
      "pricing": {
        "method": "chainlink",
        "chainlink_feed": "0x3E7d1eAB13ad0104d2750B8863b489D65364e32D",
        "pyth_feed_id": "0x2b89b9dc8fdf9f34592c9f48b082e8e61d65f4d69e2c87a74d6c5c4c4b207a3e",
        "coingecko_id": "tether",
        "_note": "Hierarchy: Chainlink (primary) → Pyth (fallback) → CoinGecko (last-resort) per Section 6.2"
      }
    },
    "0x912ce59144191c1204e64559fe8253a0e49e6548": {
      "symbol": "ARB",
      "name": "Arbitrum",
      "category": "F",
      "decimals": 18,
      "pricing": {
        "method": "kraken",
        "kraken_pair": "ARBUSD",
        "coingecko_id": "arbitrum"
      }
    },
    "0x40bd670a58238e6e230c430bbb5ce6ec0d40df48": {
      "symbol": "MORPHO",
      "name": "Morpho",
      "category": "F",
      "decimals": 18,
      "pricing": {
        "method": "kraken",
        "kraken_pair": "MORPHOUSD",
        "coingecko_id": "morpho"
      }
    },
    "0x41ca7586cc1311807b4605fbb748a3b8862b42b5": {
      "symbol": "syrupUSDC",
      "name": "Syrup USDC",
      "category": "A2",
      "decimals": 6,
      "pricing": {
        "method": "pyth",
        "pyth_feed_id": "0xe616297dab48626eaacf6d030717b25823b13ae6520b83f4735bf8deec8e2c9a",
        "coingecko_id": "syrupusdc",
        "expected_update_freq_hours": 24,
        "_note": "Maple yield-bearing USDC vault token on Arbitrum"
      }
    }
  },

  "base": {
    "native": {
      "symbol": "ETH",
      "name": "Ether",
      "category": "F",
      "decimals": 18,
      "pricing": {
        "method": "kraken",
        "kraken_pair": "ETHUSD",
        "coingecko_id": "ethereum"
      }
    },
    "0x833589fcd6edb6e08f4c7c32d4f71b54bda02913": {
      "symbol": "USDC",
      "name": "USD Coin",
      "category": "E",
      "decimals": 6,
      "pricing": {
        "method": "par",
        "depeg_check_feed": "0x8fFfFfd4AfB6115b954Bd326cbe7B4BA576818f6"
      }
    },
    "0xbaa5cc21fd487b8fcc2f632f3f4e8d37262a0842": {
      "symbol": "MORPHO",
      "name": "Morpho",
      "category": "F",
      "decimals": 18,
      "pricing": {
        "method": "kraken",
        "kraken_pair": "MORPHOUSD",
        "coingecko_id": "morpho"
      }
    },
    "0x590830dfdf9a3f68afcdde2694773debdf267774": {
      "symbol": "GIZA",
      "name": "Giza",
      "category": "F",
      "decimals": 18,
      "pricing": {
        "method": "coingecko",
        "coingecko_id": "giza"
      }
    },
    "0x944766f715b51967e56afde5f0aa76ceacc9e7f9": {
      "symbol": "avUSDC",
      "name": "Avantis USDC Vault",
      "category": "A1",
      "decimals": 6,
      "pricing": {
        "method": "a1_exchange_rate",
        "underlying": "USDC",
        "exchange_rate_contract": "0x944766f715b51967E56aFdE5f0Aa76cEaCc9E7f9",
        "exchange_rate_function": "convertToAssets",
        "_note": "ERC-4626 vault. convertToAssets(shares) returns USDC value. Underlying USDC priced at par."
      }
    },
    "0x660975730059246a68521a3e2fbd4740173100f5": {
      "symbol": "syrupUSDC",
      "name": "Syrup USDC",
      "category": "A2",
      "decimals": 6,
      "pricing": {
        "method": "pyth",
        "pyth_feed_id": "0xe616297dab48626eaacf6d030717b25823b13ae6520b83f4735bf8deec8e2c9a",
        "coingecko_id": "syrupusdc",
        "expected_update_freq_hours": 24,
        "_note": "Maple yield-bearing USDC vault token on Base"
      }
    },
    "0x1d3b1cd0a0f242d598834b3f2d126dc6bd774657": {
      "symbol": "CSUSDC",
      "name": "Clearstar USDC Reactor",
      "category": "A1",
      "decimals": 6,
      "pricing": {
        "method": "a1_exchange_rate",
        "underlying": "USDC",
        "exchange_rate_contract": "0x1D3b1Cd0a0f242d598834b3F2d126dC6bd774657",
        "exchange_rate_function": "convertToAssets",
        "_note": "Clearstar/OpenEden MetaMorpho vault (ERC-4626) on Base. Underlying USDC priced at par."
      }
    },
    "0xd7424238ccbe7b7198ab3cfe232e0271e22da7bd": {
      "symbol": "aBassyrupUSDC",
      "name": "Aave Base syrupUSDC",
      "category": "A1",
      "decimals": 6,
      "pricing": {
        "method": "pyth",
        "pyth_feed_id": "0xe616297dab48626eaacf6d030717b25823b13ae6520b83f4735bf8deec8e2c9a",
        "coingecko_id": "syrupusdc",
        "_note": "Aave aToken for syrupUSDC on Base. Balance = supplied syrupUSDC + accrued interest. Underlying (syrupUSDC) is A2."
      }
    }
  },

  "avalanche": {
    "native": {
      "symbol": "AVAX",
      "name": "Avalanche",
      "category": "F",
      "decimals": 18,
      "pricing": {
        "method": "kraken",
        "kraken_pair": "AVAXUSD",
        "coingecko_id": "avalanche-2"
      }
    },
    "0xb97ef9ef8734c71904d8002f8b6bc66dd9c48a6e": {
      "symbol": "USDC",
      "name": "USD Coin",
      "category": "E",
      "decimals": 6,
      "pricing": {
        "method": "par",
        "depeg_check_feed": "0x8fFfFfd4AfB6115b954Bd326cbe7B4BA576818f6"
      }
    },
    "0x9702230a8ea53601f5cd2dc00fdbc13d4df4a8c7": {
      "symbol": "USDT",
      "name": "Tether USD",
      "category": "E",
      "decimals": 6,
      "pricing": {
        "method": "chainlink",
        "chainlink_feed": "0x3E7d1eAB13ad0104d2750B8863b489D65364e32D",
        "pyth_feed_id": "0x2b89b9dc8fdf9f34592c9f48b082e8e61d65f4d69e2c87a74d6c5c4c4b207a3e",
        "coingecko_id": "tether",
        "_note": "Hierarchy: Chainlink (primary) → Pyth (fallback) → CoinGecko (last-resort) per Section 6.2"
      }
    }
  },

  "hyperevm": {
    "native": {
      "symbol": "HYPE",
      "name": "Hyperliquid",
      "category": "F",
      "decimals": 18,
      "pricing": {
        "method": "kraken",
        "kraken_pair": "HYPEUSD",
        "coingecko_id": "hyperliquid"
      }
    },
    "0xb88339cb7199b77e23db6e890353e22632ba630f": {
      "symbol": "USDC",
      "name": "USD Coin",
      "category": "E",
      "decimals": 6,
      "pricing": {
        "method": "par",
        "depeg_check_feed": "0x8fFfFfd4AfB6115b954Bd326cbe7B4BA576818f6"
      }
    }
  },

  "plasma": {
    "native": {
      "symbol": "XPL",
      "name": "Plasma",
      "category": "F",
      "decimals": 18,
      "pricing": {
        "method": "kraken",
        "kraken_pair": "XPLUSD",
        "coingecko_id": "plasma"
      }
    },
    "0x6100e367285b01f48d07953803a2d8dca5d19873": {
      "symbol": "WXPL",
      "name": "Wrapped XPL",
      "category": "F",
      "decimals": 18,
      "pricing": {
        "method": "kraken",
        "kraken_pair": "XPLUSD",
        "coingecko_id": "plasma"
      }
    },
    "0xb8ce59fc3717ada4c02eadf9682a9e934f625ebb": {
      "symbol": "USDT0",
      "name": "USDT0",
      "category": "E",
      "decimals": 6,
      "pricing": {
        "method": "chainlink",
        "chainlink_feed": "0x3E7d1eAB13ad0104d2750B8863b489D65364e32D",
        "pyth_feed_id": "0x2b89b9dc8fdf9f34592c9f48b082e8e61d65f4d69e2c87a74d6c5c4c4b207a3e",
        "coingecko_id": "tether",
        "_note": "USDT0 on Plasma. Hierarchy: Chainlink (primary) → Pyth (fallback) → CoinGecko (last-resort) per Section 6.2"
      }
    },
    "0xb31bea5c2a43f942a3800558b1aa25978da75f8a": {
      "symbol": "mHYPER",
      "name": "Midas Hyperithm",
      "category": "A2",
      "decimals": 18,
      "pricing": {
        "method": "chainlink",
        "chainlink_feed_chain": "plasma",
        "chainlink_feed": "0xfC3E47c4Da8F3a01ac76c3C5ecfBfC302e1A08F0",
        "expected_update_freq_hours": 168,
        "_note": "Midas Chainlink-style oracle on Plasma, NAV-based pricing",
        "_fallback_note": "No Pyth or CoinGecko feed exists for mHYPER. Midas oracle is the only available source."
      }
    },
    "0x5d3a1ff2b6bab83b63cd9ad0787074081a52ef34": {
      "symbol": "USDe",
      "name": "USDe",
      "category": "E",
      "decimals": 18,
      "pricing": {
        "method": "chainlink",
        "chainlink_feed": "0xa569d910839Ae8C109eDAA97c4eBB6a00b60C10c",
        "coingecko_id": "ethena-usde",
        "_note": "USDe on Plasma, Chainlink feed is on Ethereum mainnet"
      }
    },
    "0x211cc4dd073734da055fbf44a2b4667d5e5fe5d2": {
      "symbol": "sUSDe",
      "name": "Staked USDe",
      "category": "A1",
      "decimals": 18,
      "pricing": {
        "method": "coingecko",
        "coingecko_id": "ethena-staked-usde",
        "_note": "sUSDe on Plasma. A1 because on-chain exchange rate is authoritative. Full A1 pricing (convertToAssets) to be implemented in valuation.py"
      }
    },
    "0x7519403e12111ff6b710877fcd821d0c12caf43a": {
      "symbol": "aPlaUSDe",
      "name": "Aave Plasma USDe",
      "category": "A1",
      "decimals": 18,
      "pricing": {
        "method": "coingecko",
        "coingecko_id": "ethena-usde",
        "_note": "Aave aToken for USDe on Plasma. Balance = supplied USDe + accrued interest. Underlying (USDe) is Category E."
      }
    },
    "0xc1a318493ff07a68fe438cee60a7ad0d0dba300e": {
      "symbol": "aPlasUSDe",
      "name": "Aave Plasma sUSDe",
      "category": "A1",
      "decimals": 18,
      "pricing": {
        "method": "coingecko",
        "coingecko_id": "ethena-staked-usde",
        "_note": "Aave aToken for sUSDe on Plasma. Balance = supplied sUSDe + accrued interest. Underlying (sUSDe) is Category A1."
      }
    }
  },

  "katana": {
    "0x80c34bd3a3569e126e7055831036aa7b212cb159": {
      "symbol": "yvvbUSDC",
      "name": "vbUSDC yVault",
      "category": "A1",
      "decimals": 6,
      "pricing": {
        "method": "a1_exchange_rate",
        "underlying": "vbUSDC",
        "exchange_rate_contract": "0x80c34BD3A3569E126e7055831036aa7b212cB159",
        "exchange_rate_function": "convertToAssets",
        "_note": "Yearn V3 ERC-4626 vault on Katana. Underlying is Vault Bridge USDC (vbUSDC), pegged to USDC."
      }
    },
    "0x203a662b0bd271a6ed5a60edfbd04bfce608fd36": {
      "symbol": "vbUSDC",
      "name": "Vault Bridge USDC",
      "category": "E",
      "decimals": 6,
      "pricing": {
        "method": "par",
        "_note": "Bridge-wrapped USDC on Katana, valued at par. Vault-backed USDC representation — par pricing used as proxy for 1:1 bridge peg."
      }
    }
  },

  "solana": {
    "native": {
      "symbol": "SOL",
      "name": "Solana",
      "category": "F",
      "decimals": 9,
      "pricing": {
        "method": "kraken",
        "kraken_pair": "SOLUSD",
        "coingecko_id": "solana"
      }
    },
    "epjfwdd5aufqssqem2qn1xzybapc8g4weggkzwytdt1v": {
      "symbol": "USDC",
      "name": "USD Coin",
      "category": "E",
      "decimals": 6,
      "pricing": {
        "method": "par",
        "depeg_check_feed": "0x8fFfFfd4AfB6115b954Bd326cbe7B4BA576818f6"
      }
    },
    "es9vmfrzacermjfrf4h2fyd4kconky11mcce8benwnyb": {
      "symbol": "USDT",
      "name": "Tether USD",
      "category": "E",
      "decimals": 6,
      "pricing": {
        "method": "chainlink",
        "chainlink_feed": "0x3E7d1eAB13ad0104d2750B8863b489D65364e32D",
        "pyth_feed_id": "0x2b89b9dc8fdf9f34592c9f48b082e8e61d65f4d69e2c87a74d6c5c4c4b207a3e",
        "coingecko_id": "tether",
        "_note": "USDT on Solana. Hierarchy: Chainlink (primary, Ethereum mainnet) → Pyth (fallback) → CoinGecko (last-resort) per Section 6.2"
      }
    },
    "5y8nv33vv7wbnlfq3zbcksdyprk7g2koiqoe7m2tcxp5": {
      "symbol": "ONyc",
      "name": "OnRe Reinsurance",
      "category": "A2",
      "decimals": 9,
      "pricing": {
        "method": "pyth",
        "pyth_feed_id": "0xbabbfcc7f46b6e7df73adcccece8b6782408ed27c4e77f35ba39a449440170ab",
        "expected_update_freq_hours": 168,
        "coingecko_id": null,
        "issuer_nav_url": "https://onre.xyz",
        "_fallback_note": "No CoinGecko listing. Issuer (OnRe) publishes weekly NAV as potential manual fallback (tier 2 per Section 6.2). DEX TWAP available as last-resort."
      },
      "_token_account": "FKYixac9jrwVixJcn9JekueGsyJSg6TeJveeQVw55KUF",
      "_mint": "5Y8NV33Vv7WbnLfq3zBcKSdYPrk7g2KoiQoe7M2tcxp5"
    },
    "6frrzdk5mqargc1tdyoyvnsyrdds1t4pbtohcd6p3tgg": {
      "symbol": "USX",
      "name": "USX",
      "category": "E",
      "decimals": 6,
      "pricing": {
        "method": "pyth",
        "pyth_feed_id": "0x85d11b381ccc3e3021b7f84fa757cc01b9b5b5b1b899192b28bae7429e92926b"
      },
      "_token_account": "CvK1ZsKMNQv4BqFRkWCsLgna3sixXPpC1pNm3huKMwt1",
      "_mint": "6FrrzDk5mQARGc1TDYoyVnSyRdds1t4PbtohCD6p3tgG"
    },
    "3thdfzqkm6kryvglg48kapg5trmhymky1icra9xop1wc": {
      "symbol": "eUSX",
      "name": "eUSX (yield-bearing USX)",
      "category": "A1",
      "decimals": 6,
      "pricing": {
        "method": "a1_exchange_rate",
        "underlying": "USX",
        "underlying_mint": "6FrrzDk5mQARGc1TDYoyVnSyRdds1t4PbtohCD6p3tgG",
        "underlying_pyth_feed_id": "0x85d11b381ccc3e3021b7f84fa757cc01b9b5b5b1b899192b28bae7429e92926b"
      },
      "_token_account": "3cMZLcethiy4qb22146vbhhyJ9EZWFgn5yJVNtF6ZQht",
      "_mint": "3ThdFZQKM6kRyVGLG48kaPg5TRMhYMKY1iCRa9xop1WC"
    },
    "avzzf1yazdzipy2rck4ojrrvbbn3mtd9nl24hpeazeuaj": {
      "symbol": "syrupUSDC",
      "name": "Syrup USDC",
      "category": "A2",
      "decimals": 6,
      "pricing": {
        "method": "pyth",
        "pyth_feed_id": "0xe616297dab48626eaacf6d030717b25823b13ae6520b83f4735bf8deec8e2c9a",
        "coingecko_id": "syrupusdc",
        "expected_update_freq_hours": 24,
        "_note": "Maple yield-bearing USDC vault token on Solana"
      },
      "_mint": "AvZZF1YaZDziPY2RCK4oJrRVrbN3mTD9NL24hPeaZeUj"
    },
    "2u1tszseqz3qbwf3ungpfc8tzmk2tdiwknnrmwgwjgwh": {
      "symbol": "USDG",
      "name": "USDG",
      "category": "E",
      "decimals": 6,
      "pricing": {
        "method": "coingecko",
        "coingecko_id": "usdg",
        "_note": "USDG on Solana. Received as Kamino farming rewards."
      },
      "_mint": "2u1tszSeqZ3qBWF3uNGPFc8TzMk2tdiwknnRMWGWjGWH"
    },
    "2b1kv6dkpanxd5ixfnxcpjxmkwqjjaymc2fhsfu24gxo": {
      "symbol": "PYUSD",
      "name": "PayPal USD",
      "category": "E",
      "decimals": 6,
      "pricing": {
        "method": "par",
        "_note": "PYUSD on Solana. Received as Kamino farming rewards."
      },
      "_mint": "2b1kV6DkPAnxd5ixfnxCpjxmKwqjjaYmCZfHsFu24GXo"
    },
    "btrr3sj1bn2zjuemgbeq6sctf84ixs81cs7udtsxucak": {
      "symbol": "USCC",
      "name": "Superstate Crypto Carry Fund",
      "category": "A2",
      "decimals": 6,
      "pricing": {
        "method": "pyth",
        "pyth_feed_id": "0x5d73a5953dc86c4773adc778c30e8a6dfc94c5c3a74d7ebb56dd5e70350f044a",
        "coingecko_id": "superstate-uscc",
        "expected_update_freq_hours": 24,
        "issuer_nav_url": "https://superstate.com/assets/uscc",
        "cross_ref_url": "https://superstate.com/assets/uscc",
        "_note": "USCC on Solana (Kamino Superstate Opening Bell collateral). Hierarchy: Pyth (primary) → Superstate daily NAV (tier 2 issuer) → CoinGecko (fallback)."
      },
      "_mint": "BTRR3sj1Bn2ZjuemgbeQ6SCtf84iXS81CS7UDTSxUCaK"
    },
    "3kctcxgt6pp3uzcek8sqnk2kzdq6cqtj9hc3u46jhgbk": {
      "symbol": "PT-USX-01JUN26",
      "name": "PT USX 01-Jun-2026 (Exponent)",
      "category": "B",
      "decimals": 6,
      "pricing": {
        "method": "pt_linear_amortisation",
        "underlying": "USX",
        "maturity": "2026-06-01",
        "_note": "Kamino Solstice collateral. Priced per Category B lot methodology (linear amortisation per individual lot)."
      },
      "_mint": "3kctCXgt6pP3uZcek8SqNK2KZdQ6cqtj9hc3U46jhgBk"
    },
    "bnr2fsho8jrygwx2v8yxg5gbwiig3uu8voi2emgbhfwej": {
      "symbol": "PT-eUSX-01JUN26",
      "name": "PT eUSX 01-Jun-2026 (Exponent)",
      "category": "B",
      "decimals": 6,
      "pricing": {
        "method": "pt_linear_amortisation",
        "underlying": "eUSX",
        "maturity": "2026-06-01",
        "_note": "Kamino Solstice collateral. Priced per Category B lot methodology (linear amortisation per individual lot)."
      },
      "_mint": "BNR2FsHo8JrYGWx2V8yxG5GBWiG3uU8voi2eMGBHFwEj"
    },
    "524c555344000000000000000000000000000000.rmxckbedwqr76quhesumdef4b9xj8m5de": {
      "symbol": "RLUSD",
      "name": "Ripple USD",
      "category": "E",
      "decimals": 6,
      "pricing": {
        "method": "par",
        "pyth_feed_id": "0x65652029e7acde632e80192dcaa6ea88e61d84a4c78a982a63e98f4bbcb288d5",
        "coingecko_id": "ripple-usd",
        "_note": "RLUSD on Solana. Issued by Standard Custody & Trust Company (Ripple Labs subsidiary). Pyth feed used for depeg monitoring."
      },
      "_mint": "524C555344000000000000000000000000000000.rMxCKbEDwqr76QuheSUMdEGf4B9xJ8m5De"
    }
  }
}
